setup.py
BGGDistributions/Binomialdistribution.py
BGGDistributions/Gaussiandistribution.py
BGGDistributions/Generaldistribution.py
BGGDistributions/__init__.py
BGGDistributions.egg-info/PKG-INFO
BGGDistributions.egg-info/SOURCES.txt
BGGDistributions.egg-info/dependency_links.txt
BGGDistributions.egg-info/not-zip-safe
BGGDistributions.egg-info/top_level.txt