Metadata-Version: 1.0
Name: BGGDistributions
Version: 0.1
Summary: Gaussian, Binomail, and General distributions
Home-page: UNKNOWN
Author: UNKNOWN
Author-email: UNKNOWN
License: UNKNOWN
Platform: UNKNOWN
